{
   "results" : [
      {
         "address_components" : [
            {
               "long_name" : "Los Angeles County",
               "short_name" : "Los Angeles County",
               "types" : [ "administrative_area_level_2", "political" ]
            },
            {
               "long_name" : "California",
               "short_name" : "CA",
               "types" : [ "administrative_area_level_1", "political" ]
            },
            {
               "long_name" : "United States",
               "short_name" : "US",
               "types" : [ "country", "political" ]
            }
         ],
         "formatted_address" : "Los Angeles County, CA, USA",
         "geometry" : {
            "bounds" : {
               "northeast" : {
                  "lat" : 34.8231929,
                  "lng" : -117.6456041
               },
               "southwest" : {
                  "lat" : 32.7983762,
                  "lng" : -118.9449036
               }
            },
            "location" : {
               "lat" : 34.0522265,
               "lng" : -118.2436596
            },
            "location_type" : "APPROXIMATE",
            "viewport" : {
               "northeast" : {
                  "lat" : 34.8231929,
                  "lng" : -117.6456041
               },
               "southwest" : {
                  "lat" : 33.7036917,
                  "lng" : -118.9449036
               }
            }
         },
         "place_id" : "ChIJMc1kAdMq3YARKjm9z9YofYM",
         "types" : [ "administrative_area_level_2", "political" ]
      }
   ],
   "status" : "OK"
}
